README.rst
setup.py
modrezip/__init__.py
modrezip.egg-info/PKG-INFO
modrezip.egg-info/SOURCES.txt
modrezip.egg-info/dependency_links.txt
modrezip.egg-info/pbr.json
modrezip.egg-info/top_level.txt
modrezip.egg-info/zip-safe
test/test.py