Metadata-Version: 1.0
Name: modrezip
Version: 1.0.0
Summary: module for creating a modified copy of a zip file
Home-page: https://github.com/nicholasbishop/modrezip
Author: Nicholas Bishop
Author-email: nicholasbishop@gmail.com
License: Apache License 2.0
Platform: UNKNOWN
